sppa
